k_lights_interface/__init__.py
k_lights_interface/k_ble_manager.py
k_lights_interface/k_ble_transport.py
k_lights_interface/k_capabilities.py
k_lights_interface/k_color_sort.py
k_lights_interface/k_device.py
k_lights_interface/k_device_names.py
k_lights_interface/k_logging.py
k_lights_interface/k_serial_manager.py
k_lights_interface/k_serial_transport.py
k_lights_interface/k_singleton.py
k_lights_interface/k_transport.py
k_lights_interface/proto_protocol/__init__.py
k_lights_interface-0.2.4.dist-info/METADATA
k_lights_interface-0.2.4.dist-info/WHEEL
k_lights_interface-0.2.4.dist-info/licenses/LICENSE
k_lights_interface-0.2.4.dist-info/RECORD
