Metadata-Version: 2.4
Name: k-lights-interface
Version: 0.2.4
Summary: A package to control Kelvin lights using usb or bluetooth. Set cct, hsi, rgb, rgbacl, read out various data and more.
Project-URL: Homepage, https://github.com/KelvinLights/k-lights-interface-py
Project-URL: Bug Tracker, https://github.com/KelvinLights/k-lights-interface-py/issues
Author-email: bjorn <developer@riftlabs.com>
License-File: LICENSE
Classifier: License :: OSI Approved :: MIT License
Classifier: Operating System :: OS Independent
Classifier: Programming Language :: Python :: 3.10
Requires-Python: >=3.10
Requires-Dist: betterproto==2.0.0b7
Requires-Dist: betterproto[compiler]==2.0.0b7
Requires-Dist: bleak
Requires-Dist: grpcio-tools
Requires-Dist: markupsafe==2.0.1
Requires-Dist: nest-asyncio
Requires-Dist: numpy
Requires-Dist: ordered-set
Requires-Dist: pyserial
